expyct/__init__.py
expyct/__version__.py
expyct/_patch.py
expyct/any.py
expyct/base.py
expyct/collection.py
expyct/combination.py
expyct/datetime.py
expyct/number.py
expyct/string.py
expyct-1.1.0.dist-info/LICENSE
expyct-1.1.0.dist-info/METADATA
expyct-1.1.0.dist-info/WHEEL
expyct-1.1.0.dist-info/top_level.txt
expyct-1.1.0.dist-info/RECORD
