Metadata-Version: 2.1
Name: expyct
Version: 1.1.0
Summary: Partial matching of any object
Home-page: https://github.com/mthaak/expyct
Author: mthaak
Author-email: mthaak.dev@gmail.com
License: MIT
Project-URL: Source Code, https://github.com/mthaak/expyct
Project-URL: Documentation, https://mthaak.github.io/expyct/
Platform: UNKNOWN
Classifier: Development Status :: 5 - Production/Stable
Classifier: Programming Language :: Python :: 3.6
Classifier: Programming Language :: Python :: 3.7
Classifier: Programming Language :: Python :: 3.8
Classifier: Programming Language :: Python :: 3.9
Classifier: Operating System :: OS Independent
Classifier: Topic :: Software Development :: Testing
Requires-Python: >=3.6
